<item>
  <category>aeroplane</category>
  <ap>0.6173729366442663</ap>
</item>
<item>
  <category>bicycle</category>
  <ap>0.47574918243051945</ap>
</item>
<item>
  <category>bird</category>
  <ap>0.5930388713351271</ap>
</item>
<item>
  <category>boat</category>
  <ap>0.3310966606416864</ap>
</item>
<item>
  <category>bottle</category>
  <ap>0.39620920056070424</ap>
</item>
<item>
  <category>bus</category>
  <ap>0.6747216420065683</ap>
</item>
<item>
  <category>car</category>
  <ap>0.5350081259750041</ap>
</item>
<item>
  <category>cat</category>
  <ap>0.7023067236180943</ap>
</item>
<item>
  <category>chair</category>
  <ap>0.2937054331297706</ap>
</item>
<item>
  <category>cow</category>
  <ap>0.5865104460326361</ap>
</item>
<item>
  <category>diningtable</category>
  <ap>0.21447306791569085</ap>
</item>
<item>
  <category>dog</category>
  <ap>0.675465369690163</ap>
</item>
<item>
  <category>horse</category>
  <ap>0.6519881911849027</ap>
</item>
<item>
  <category>motorbike</category>
  <ap>0.5286566724227849</ap>
</item>
<item>
  <category>person</category>
  <ap>0.6381563860706868</ap>
</item>
<item>
  <category>pottedplant</category>
  <ap>0.274485369286075</ap>
</item>
<item>
  <category>sheep</category>
  <ap>0.6036650911270901</ap>
</item>
<item>
  <category>sofa</category>
  <ap>0.30949759012916933</ap>
</item>
<item>
  <category>train</category>
  <ap>0.5932031436860064</ap>
</item>
<item>
  <category>tvmonitor</category>
  <ap>0.5797209030463192</ap>
</item>
